setup.py
anish/__init__.py
anish.egg-info/PKG-INFO
anish.egg-info/SOURCES.txt
anish.egg-info/dependency_links.txt
anish.egg-info/top_level.txt