Metadata-Version: 2.1
Name: anish
Version: 0.0.1
Summary: anish
Home-page: UNKNOWN
Author: Anish Agrawal
Author-email: your.email@example.com
License: UNKNOWN
Platform: UNKNOWN
